mindsdb_server/__about__.py
mindsdb_server/__init__.py
mindsdb_server/server.py
mindsdb_server/shared_ressources.py
mindsdb_server/namespaces/__init__.py
mindsdb_server/namespaces/datasource.py
mindsdb_server/namespaces/predictor.py
mindsdb_server/namespaces/util.py
mindsdb_server/namespaces/configs/__init__.py
mindsdb_server/namespaces/configs/datasources.py
mindsdb_server/namespaces/configs/predictors.py
mindsdb_server/namespaces/configs/util.py
mindsdb_server/namespaces/entitites/__init__.py
mindsdb_server/namespaces/entitites/column_metadata.py
mindsdb_server/namespaces/entitites/data_analysis_metadata.py
mindsdb_server/namespaces/entitites/data_distribution_metadata.py
mindsdb_server/namespaces/entitites/data_preparation_metadata.py
mindsdb_server/namespaces/entitites/histogram_data.py
mindsdb_server/namespaces/entitites/label_group.py
mindsdb_server/namespaces/entitites/nested_histogram_data.py
mindsdb_server/namespaces/entitites/predictor_metadata.py
mindsdb_server/namespaces/entitites/predictor_status.py
mindsdb_server/namespaces/entitites/quality_dimension.py
mindsdb_server/namespaces/entitites/quality_metric.py
mindsdb_server/namespaces/entitites/target_column_metadata.py
mindsdb_server/namespaces/entitites/datasources/__init__.py
mindsdb_server/namespaces/entitites/datasources/datasource.py
mindsdb_server/namespaces/entitites/datasources/datasource_data.py
mindsdb_server/namespaces/entitites/datasources/datasource_files.py
mindsdb_server/namespaces/entitites/datasources/datasource_missed_files.py
mindsdb_server-1.2.2.dist-info/LICENSE
mindsdb_server-1.2.2.dist-info/METADATA
mindsdb_server-1.2.2.dist-info/WHEEL
mindsdb_server-1.2.2.dist-info/top_level.txt
mindsdb_server-1.2.2.dist-info/RECORD
