Metadata-Version: 2.1
Name: mindsdb-server
Version: 1.2.2
Summary: MindsDB server, provides server capabilities to mindsdb native python library
Home-page: https://github.com/mindsdb/mindsdb_server
Author: MindsDB Inc
Author-email: jorge@mindsdb.com
License: MIT
Download-URL: https://pypi.org/project/mindsdb-server/
Platform: UNKNOWN
Classifier: Programming Language :: Python :: 3
Classifier: License :: OSI Approved :: MIT License
Classifier: Operating System :: OS Independent
Requires-Python: >=3.6
Requires-Dist: mindsdb
Requires-Dist: flask
Requires-Dist: flask-restplus
